{
  "required": true,
  "package": "snownee.kaleido.mixin",
  "compatibilityLevel": "JAVA_8",
  "refmap": "kaleido.refmap.json",
  "mixins": [
    "MixinDebugChunkGenerator"
  ],
  "client": [
    "MixinModelBakery",
    "MixinBlockModelRenderer",
    "MixinBlock",
    "MixinMinecraft",
    "MixinClientModLoader",
    "ctm.MixinCTMLogic",
    "jei.MixinItemStackListFactory",
    "buildinggadgets.MixinBaseRenderer",
    "buildinggadgets.MixinCopyPasteRender",
    "buildinggadgets.MixinBuildRender",
    "buildinggadgets.MixinEffectBlockTER"
  ],
  "injectors": {
    "defaultRequire": 1
  },
  "minVersion": "0.8"
}
